{
  "monthlyCosts": [
    {
      "buildingId": 1,
      "buildingName": "Sunset Tower",
      "month": "2026-05",
      "utilities": 6200,
      "maintenance": 8400,
      "cleaning": 3900,
      "security": 5200,
      "insurance": 4100,
      "propertyTax": 9600,
      "managementFee": 3400,
      "total": 40800
    },
    {
      "buildingId": 2,
      "buildingName": "Green Park Residences",
      "month": "2026-05",
      "utilities": 5100,
      "maintenance": 6800,
      "cleaning": 3200,
      "security": 4300,
      "insurance": 3500,
      "propertyTax": 7900,
      "managementFee": 2800,
      "total": 33600
    },
    {
      "buildingId": 3,
      "buildingName": "Downtown Plaza",
      "month": "2026-05",
      "utilities": 8300,
      "maintenance": 11200,
      "cleaning": 5200,
      "security": 7100,
      "insurance": 5700,
      "propertyTax": 13400,
      "managementFee": 4500,
      "total": 55400
    },
    {
      "buildingId": 4,
      "buildingName": "Riverside Apartments",
      "month": "2026-05",
      "utilities": 3400,
      "maintenance": 4600,
      "cleaning": 2300,
      "security": 2900,
      "insurance": 2400,
      "propertyTax": 5200,
      "managementFee": 1900,
      "total": 22700
    },
    {
      "buildingId": 5,
      "buildingName": "Mountain View Heights",
      "month": "2026-05",
      "utilities": 5600,
      "maintenance": 7200,
      "cleaning": 3400,
      "security": 4600,
      "insurance": 3800,
      "propertyTax": 8400,
      "managementFee": 3000,
      "total": 36000
    }
  ]
}
